accessiqlue/__init__.py
accessiqlue/main.py
accessiqlue/prompts.py
accessiqlue-2025.12.21154255.dist-info/METADATA
accessiqlue-2025.12.21154255.dist-info/WHEEL
accessiqlue-2025.12.21154255.dist-info/top_level.txt
accessiqlue-2025.12.21154255.dist-info/RECORD
