Metadata-Version: 2.4
Name: accessiqlue
Version: 2025.12.21154255
Summary: A new package designed to take user input about accessibility challenges and generate structured summaries or actionable recommendations. It leverages advanced pattern matching with language model int
Author-email: accessiqlue <hi@eugene.plus>
License: MIT
Project-URL: Homepage, https://github.com/chigwell/accessiqlue
Requires-Python: >=3.9
Requires-Dist: langchain-llm7>=0.0.0
Requires-Dist: llmatch-messages>=0.0.0
Requires-Dist: langchain-core>=0.3.0
